clean_docker/__init__.py
clean_docker/cli.py
clean_docker/main.py
clean_docker-1.1.1.dist-info/LICENSE
clean_docker-1.1.1.dist-info/METADATA
clean_docker-1.1.1.dist-info/WHEEL
clean_docker-1.1.1.dist-info/entry_points.txt
clean_docker-1.1.1.dist-info/top_level.txt
clean_docker-1.1.1.dist-info/RECORD
