Metadata-Version: 2.1
Name: clean-docker
Version: 1.1.1
Summary: The CLI tool to remove all Docker artifacts from the machine
Home-page: https://github.com/lancelote/clean-docker
Author: Pavel Karateev
Author-email: lancelote.du.lac@gmail.com
License: MIT
Platform: UNKNOWN
Classifier: License :: OSI Approved :: MIT License
Classifier: Programming Language :: Python :: 3
Classifier: Programming Language :: Python :: 3 :: Only
Classifier: Programming Language :: Python :: 3.8
Classifier: Programming Language :: Python :: 3.9
Classifier: Programming Language :: Python :: Implementation :: CPython
Requires-Python: >=3.8
Requires-Dist: click
Requires-Dist: docker
Requires-Dist: importlib-metadata ; python_version < "3.8"
